base2048-0.1.3.dist-info/METADATA
base2048-0.1.3.dist-info/WHEEL
base2048-0.1.3.dist-info/license_files/LICENSE
base2048/py.typed
base2048/__init__.py
base2048/base2048.pyi
base2048/base2048.abi3.so
base2048-0.1.3.dist-info/RECORD
