Metadata-Version: 2.1
Name: base2048
Version: 0.1.3
Classifier: Programming Language :: Rust
Classifier: Programming Language :: Python :: Implementation :: CPython
Classifier: Programming Language :: Python :: Implementation :: PyPy
Classifier: Programming Language :: Python :: 3.7
Classifier: Programming Language :: Python :: 3.8
Classifier: Programming Language :: Python :: 3.9
Classifier: Programming Language :: Python :: 3.10
Classifier: Programming Language :: Python :: 3.11
Requires-Dist: frelatage; extra == 'fuzz'
Requires-Dist: maturin; extra == 'dev'
Requires-Dist: pytest; extra == 'dev'
Requires-Dist: pytest-cov; extra == 'dev'
Provides-Extra: fuzz
Provides-Extra: dev
License-File: LICENSE
Summary: Binary encoding with Base2048 in Rust.
Keywords: base2048,base64,base-encoding,encoding,decoding
License: MIT
Requires-Python: >=3.7
